{"asin": "B005HEUUEA", "description": "What's this bag all about?More Berlin than Berkeley, the Command's oxford nylon and anodized hardware make it Timbuk2's most sophisticated bag. Paired with a TSA compliant crater sleeve with separate laptop and iPad pockets, it&rsquo;s a free upgrade magnet.", "title": "Timbuk2 Command Laptop TSA-Friendly Messenger Bag", "imUrl": "http://ecx.images-amazon.com/images/I/411JqM8q2vL._SY300_.jpg", "related": {"also_bought": ["B002WC8ZGA", "B002HU27UW", "B00714FK2G", "B00HZ16WJU", "B002WC8ZII", "B0068DU8BY", "B002T0HRVY", "B002VPE1QG", "B008VSZ8ZK", "B004VD8TKK", "B004MMEHKG", "B00HZ15TEY", "B005GD9W46", "B00DDY7IKU", "B00479FQCM", "B002XVYZ82", "B00HJ8DFGC", "B001CDD0X8", "B00DQV6L6C", "B0093IRVDE", "B00D5VAYRU", "B00EK8BB6U", "B001E1Y5O6", "B00EF1OGOG", "B003MU9K24", "0671316338", "B00006IFIR", "B000WO84Z2", "B00IBDOB5I", "B0073FCPSK", "B00FS8JPXW", "B005NGLTZQ"], "also_viewed": ["B00HZ15TEY", "B0080B834Q", "B0068DU8BY", "B003386CVC", "B00AMXVFIQ", "B004VD7AGO", "B00HZ176E0", "B00338D26A", "B00DR7H042", "B002WC8ZGA", "B00J2Y4W2W", "B00KPPWCHY", "B006L8KRXA", "B00ESI1P5Y", "B00714CREK", "B00J2Y46SW", "B00E7OT84Y", "B0029L7N9E", "B004VD85FO", "B00HZ173I4", "B00HZ17KVY", "B00BQU0ZRG", "B0048CL50K", "B002VECWXG", "B002WC8ZII", "B003KYTOIC", "B0055BLLIY", "B00AYM223W", "B00HZ18IVK", "B001KWLLS2", "B004VD7IXE", "B008KNVBPC", "B00BHHBM9S", "B00JLAM4F4", "B00FVRDR3E", "B0088WIP6I", "B00D1OO61G", "B00E1O4KK2", "B003V1XEDU", "B00KPPXBAQ", "B004VD8TKK", "B00BHHBNC4", "B00EI2WD2O", "B0031Q1KMC", "B00714FK2G", "B0029XFHKO", "B0088WKFA2", "B00FDVJCGO", "B002NU5O4W", "B00GPDJ2O6", "B002VECWX6", "B00FVBKBTI", "B008YVKHSW", "B00EDQJTOK"], "bought_together": ["B002HU27UW", "B002VPE1QG"]}, "salesRank": {"Sports &amp; Outdoors": 2758}, "categories": [["Electronics", "Computers & Accessories", "Laptop & Netbook Computer Accessories", "Bags & Cases", "Messenger Bags"]]}