{"asin": "B00539LU3E", "description": "The TUF Series delivers preeminent stability, all-around compatibility, and extreme durability, providing the most reliable computing experience.", "title": "ASUS Sabertooth 990FX AM3+ AMD 990FX SATA 6Gb/s USB 3.0 ATX AMD Motherboard", "price": 170.27, "imUrl": "http://ecx.images-amazon.com/images/I/515TK-vtRxL._SX300_.jpg", "related": {"also_bought": ["B005UBNLFK", "B005UBNKZG", "B004RFBIUU", "B004CRSM4I", "B009O7YUF6", "B005UBNKWO", "B006EWUO22", "B0036Q7MV0", "B002SRQ214", "B004E0ZKLQ", "B004MYFODI", "B0056KUWS4", "B004Q0PT3I", "B0033Z2BAQ", "B003ZM7YTA", "B004CRSM52", "B004ZMG55I", "B0057FRTPW", "B007R1FH3K", "B004XUCCS6", "B0051U7HMS", "B001IZ7MHU", "B005UBNL0A", "B004W2JKZI", "B0088PK040", "B000OGX5AM", "B004SUO068", "B004MYFOE2", "B004WK3KKQ", "B003O8J11E", "B009O7YU56", "B003PJ6QW4", "B004MYFODS", "B00596U0YQ", "B008YDJHWM", "B00461G3MS", "B002RRLQIO", "B004LB5AZY", "B0026ZPFCK", "B005O65JXI", "B0068ZWZY0", "B003JZCF2O", "B00461LT6S", "B002I8MUU0", "B001G0WPLK", "B002DUKPN2", "B007QY87MG", "B006B7R9PU", "B007RARHSO", "B004VFJ9MK", "B004X8EODY", "B002LE8BJA", "B0046U6DWO", "B006EKJCWM", "B0055Q7BR4", "B005T3GRN2", "B0092ML0OC", "B0046U6DTC", "B002ZV51DI", "B009ZN03AA", "B00713RTQ2", "B007H2OHBC", "B005XJWQKU", "B004SU8AUU", "B004O6MOC8", "B007JLFV7U"], "buy_after_viewing": ["B008YDJHWM", "B009O7YUF6", "B000OGX5AM", "B008B6ONXK"]}, "categories": [["Electronics", "Computers & Accessories", "Computer Components", "Motherboards"]]}