{"asin": "B000U0HRKG", "related": {"also_bought": ["B001EO10IW", "B001EO7OKA", "B007A9NSR6", "B006Q3LUUY", "B002ROEKBW", "B00LMBURDG", "B00471HK0Q", "B009GGC4B2", "B004LHJD4M", "B004VSA7GO", "B0077G5BTA", "B003626OFO", "B00HNFN7BE", "B00IMS8MI4", "B000U0E08I", "B00LMBURV8", "B0056DV0L4", "B002RT85RW", "B003624UMI", "B004477BQQ", "B009KXE4VO", "B000U0HRJM", "B0040NOWY8", "B00LPUO24Y", "B001FSBZNC", "B00465XLWO", "B008YQAFWU", "B00DUHUPCS", "B0001MKU48", "B00AXYQGKG", "B00AO1XFM0", "B00HNFO4RU", "B003624USC", "B000A0CV9S", "B00L4K3MLE", "B004K4THQK", "B004S6315S", "B0039825U8", "B00LLAV26O", "B00JV054A6", "B00L9K2EGS", "B00BLB4L7K", "B008YQAGF6", "B004VS8VA8", "B002ROAZE8", "B005AT3F1W", "B001DYZAZM", "B001E032X2", "B002ROAZ20", "B00IKM5N1G", "B00DYEN6XC", "B0096D83ZG", "B00K7IPGS6", "B0074BPFW6", "B00ISS5F6A", "B0089C2LRG", "B002LU9EXG", "B00HWHC3RM", "B00K1L4NBU", "B001J0K9RO", "B00E9PMMPI", "B008M1B3R8", "B002RO8QVW", "B00AIBZMM2", "B00HWWUQYY", "B0081CVAQ2", "B00HERGM86", "B00GST8UB8", "B00JPS6A3O", "B00CNIDGXK", "B00KUS5YBM", "B006M6Q97O", "B00IQAUO5C", "B003EE08S8", "B00G0OHMUG", "B00H9KKKAY", "B005LAIHY0", "B00H83EV5W", "B003626OC2", "B008MCZJXG", "B004Z7SFCE", "B00GHH9GSC", "B0090SI582", "B00EPA3V7A", "B00JJOY496", "B008JFUR10", "B000EIXWPI", "B00HW3LCCI", "B00HZN8S9U", "B00ID3TPD4", "B00361ZJQU", "B00JVLGL2A", "B008YQAG5Q", "B00EL6ACBQ", "B003626OD6", "B00BEJL6Q8", "B007AJMC4Q", "B008JFUO0Y", "B000XJ5TOK"], "bought_together": ["B00471HK0Q"], "buy_after_viewing": ["B009GGC4B2", "B004LHJD4M", "B00HNFO4RU", "B00HNFN7BE"]}, "title": "25 x Empty Standard Blue Replacement Boxes/Cases for Blu-Ray DVD Movies (DVBR12BR)", "price": 12.9, "salesRank": {}, "imUrl": "http://ecx.images-amazon.com/images/I/41Ezhlptb9L._SX300_.jpg", "brand": "SuperMediaStore", "categories": [["Electronics", "Accessories & Supplies", "Audio & Video Accessories", "Media Storage & Organization", "DVD Cases"]], "description": "N/A"}