{"asin": "B002V5OYHC", "description": "Jam to your favorite tunes from your Bluetooth-enabled MP3 player, cell phone or other audio device using these behind-the-head Bluetooth headphones that feature 4 high-definition audio settings for stunning audio quality. What's Included Rocketfish Bluetooth High-Definition Stereo Headphones for Most Bluetooth-Enabled Devices USB charging cable AC adapter Owner's manual", "title": "Rocketfish Bluetooth High-Definition Stereo Headphones for Most Bluetooth-Enabled Devices Black RF-MAB2", "price": 34.99, "imUrl": "http://ecx.images-amazon.com/images/I/41a5enYvlAL._SX300_.jpg", "related": {"also_bought": ["B009YKTR06", "B001EBE1LI", "B001D8CCYK", "B0019UX796", "B002BH3I9U", "B00AWIPITS", "B004SH40BQ", "B005LKB0IU", "B00E0GRRR4", "B00EDPW2Q8", "B007Q45EF4"], "buy_after_viewing": ["B002BH3I9U", "B00AWIPITS", "B00E0GRRR4", "B005LKB0IU"]}, "categories": [["Electronics", "Accessories & Supplies", "Audio & Video Accessories", "Headphones"]]}