{"asin": "B00004SYNX", "related": {"also_bought": ["B0000XKBQU", "B00005125T", "B00023433U", "B00461G3MS", "B00006JI5H", "B003CFATNI", "B007MWYCG2", "B0030TK3FA", "B001CY0P7G", "B0049MPQA4", "B0006I09OS", "B000SSUHO8", "B004B0H69I", "B0009MIP8I", "B002G1YPHK", "B0000TO0BQ", "B00461K1QW", "B0034CSUZ8", "B00003006K", "B0064GON70", "B003FP95Q2", "B004KABG1S", "B001R4BT1M", "B002DKRDXC", "B0012MZAH8", "B0037NYQ7K", "B0088PUEPK", "B004LR1RPK", "B001Q7X0Z8", "B00461E7JE", "B00005LLY4", "B0054OWT0G", "B000RO3BPA", "B000BKBVT8", "B004XFYGNK", "B004BQKQ8A", "B00002EQCW", "B002YIG9AQ", "B00009YFTI", "B001ISJ964", "B0009RPY96", "B00H09BOXQ", "B005IUW7YE", "B005NBP9UW", "B001CO3EKQ", "B002URUI80", "B000F4C310", "B004MU8VCS", "B005CT56R6", "B002K0TU2C", "B00484IEJS", "B00002EQCS", "B00DSUTWMQ", "B004F3DJYC", "B00116SLYY", "B0019804U8", "B005CYXW7M", "B003NREDC8", "B00EZKO8J0", "B003CH6ZR0", "B00006IRR8", "B00COGDERY", "B00D601UC8", "B000I5HE38", "B000YJIJI2", "B008968L6M", "B0037NYQ6Q", "B0011A4UZE", "B001P92AA8", "B000F6KQ7G", "B00H09BO2M", "B00C9TECFO", "B001B2M9FU", "B0007T27H8", "B0033Z2BAQ", "B003N8GVUY", "B005MEDD80", "B001OZFCI0", "B004LT8MN8", "B000JFJZGG", "B00007IFED", "B0098Y77U0", "B000FBK3QK", "B0039L31JY", "B009SPWJ98", "B006TZM6XO", "B000Z80ICM", "B0000BVYT3", "B000G6U2W4", "B003WOWB5S", "B004H5C0WK", "B001985SWW", "B003D3MFHM", "B001D1UTC4", "B005J1SUIO", "B002EAAS8S", "B004KABG1I", "B007B5YUMQ", "B001JYVFLY", "B00115TE0K"], "bought_together": ["B00023433U"], "buy_after_viewing": ["B00023433U", "B0034CSUZ8", "B0000XKBQU", "B00005125T"]}, "title": "D-Link DFE-530TX+ 10/100 Fast Ethernet Desktop Adapter", "price": 9.99, "salesRank": {}, "imUrl": "http://ecx.images-amazon.com/images/I/31jabDlMTuL._SX300_.jpg", "brand": "D-Link", "categories": [["Electronics", "Computers & Accessories", "Networking Products", "Network Adapters", "USB Network Adapters"]], "description": "The D-Link DFE-530TX Wakeup-on-LAN NIC is an Ethernet adapter for PCs, high-end workstations, and workgroup file servers. Realtek's RTL8139A single-chip Fast Ethernet controller uses the bus master burst mode to directly transfer data between the card and the host computer's memory. This spares the host's workload by bypassing its CPU. This PCI adapter eliminates network bottlenecks and also works with videographic or multimedia stations.Plug-and-play installation gets you up and running in no time. The software supports Windows for Workgroups; Windows 95, 98, and NT; LanMan; Novell; and Linux.D-Link provides a lifetime warranty."}