{"asin": "B008IEGS9W", "description": "HardBack for Google Nexus 7 7-Inch Tablet features and all in one design with ultra thin hard plastic tray for protection the back of your Google Nexus 7 7-Inch Tablet Soft microfiber interior lining offers anti-slip protection when roll back cover is in typing position, and adds much needed scratch protection for your screen Flip out spin design adds multiple viewing positions while in landscape mode All ports, buttons, and camera is perfectly exposed for un-hindered use while your Google Nexus 7 7-Inch Tablet is protected Made for Google Nexus 7 7-Inch Tablet. Made by Poetic", "title": "Poetic StrapBack Protective Case for the Google Nexus 7 Android Tablet by Asus", "price": 3.95, "imUrl": "http://ecx.images-amazon.com/images/I/41CUyFtx8pL._SX300_.jpg", "related": {"also_bought": ["B00LAEDWPA", "B00L9L0U8G", "B00L9L0TYG", "B00LFWL4MU", "B00KLL5CCY", "B00LBI2U76", "B00KXFOAVM", "B00LBI2TCW", "B00L9L0QM6", "B00LT23AX2", "B00LBI2VZW", "B00KGLBZO8", "B00KHBQOPW", "B00KXFO7WY", "B00KNKSZ3G", "B00KXFOR1U", "B00KGLC2PE", "B00KC2D0PS", "B00KHBQFZG", "B00L9L0P8G", "B00L9L0S6A", "B00LAED8FO", "B00KHBQC0E", "B00KXFOFZS", "B00KXFOSMS", "B00L9L0T8C", "B00L9L0SZG", "B00KGLC5F6", "B00KC2CICE", "B00KC2CK6S", "B00IZ0YZNU", "B00EX9JAW8", "B00KGLCKMO", "B00KC2D3A0", "B00KXFOMX8", "B00KXFOO04", "B00EX9JASM", "B00KGLC3ZS", "B00IO59ZUY", "B00E5NOWTS", "B00LH5XWB6", "B00K8AFBEC", "B00J9VY08O", "B00J3692CE", "B00ISF2FXE", "B00KC2CGSU", "B00J39DKEW", "B00JBMC4MA", "B00KGLCRAE", "B00EX9J9L0", "B00JBMC64Q", "B00KXFON1O", "B00IU4AT3G", "B00IU4AUNK", "B00EX9JAA0", "B00LBI3B6K", "B00JBMC5F6", "B00JG5IOEO", "B00EX9JA78", "B00J2D5HW2", "B00J2D5I4O", "B00JAR24SU", "B00J4YWJ1Q", "B00JFIO43W", "B00IMMRGDM", "B00E7FY7D0", "B00FNCSS2W", "B00I2XHLOA", "B00LEY94L2", "B00KLL5AEE", "B00JFIO6K8", "B00KGLCOFW", "B00JDR6MM6", "B00D9D74ZY", "B00KXFOKYO", "B00EX9JAGO", "B00JDR6ICU", "B00JDR6KQO", "B00JPPENHW", "B00GQM1WYY", "B00EX9J9DI", "B00FNCSTLM", "B00JJZL9FM", "B00JMMLJS4", "B0093CDLM0", "B00KLL5CNS", "B00CW1N6CY", "B00J2D5J70", "B00IRLEHHG", "B00JFIO5IG", "B00EAY7MBM", "B00IZLP3Q2", "B00I2XHJWE", "B00K1L2JA2", "B00HNHCR0O", "B00ACVI202", "B00E7FYAT6", "B00CW1N6R4"], "bought_together": ["B00J39DKEW"], "buy_after_viewing": ["B00E5NOXM4", "B00CKA1IYU", "B00DVFLJKQ", "B00E9QK7X6"]}, "categories": [["Electronics", "Computers & Accessories", "Touch Screen Tablet Accessories", "Cases & Sleeves", "Cases"]]}