{"asin": "B004LLRYOY", "description": "Square Enix FF IV:The Complete CollectionFinal Fantasy IV:The Complete Collection PSP", "price": 19.99, "imUrl": "http://ecx.images-amazon.com/images/I/517VNiM7sbL._SY300_.jpg", "related": {"also_bought": ["B000NPOGWK", "B000NPTOTK", "B002I0GXWO", "B000SSPH3E", "B0014X7SQ6", "B003YVK5T8", "B001TD6SN0", "B002E6XY6K", "B000R37S78", "B004BV5O0U", "B000G0O6CW", "B000R37S00", "B000CI83LI", "B001CM0PJ6", "B002I0GZ5Y", "B001KMRN0M", "B003O21OWY", "B00523VFJU", "B000CBCVEK", "B001CM62UM", "B008BERJEM", "B004R0TR0S", "B000GABOTU", "B001V7UX1W", "B000VIPJ0W", "B002BS47TE", "B000HE9LEK", "B001HWF1OA", "B006O3Z2ZA", "B00002R28C", "B000R39IKI", "B001GXI4LM", "B000FG65F8", "B000TTZI0E", "B00184219U", "B005EYJ4PO", "B000CBCVF4", "B000LY4IDK", "B002I09830", "B000FG65EY", "B00004Y57G", "B007ZH9OFI", "B0010YOQIW", "0744009383", "B002DMJ0RM", "B003Q9RG9K", "B000FDOTIQ", "B000ASBKHE", "B00KVRK39A", "B0016QCCG2", "B002DGNLFK", "B00BY0G0YU", "B001IB1YOQ", "B00127VDWY", "B00L3LQ1FI", "B000SSQPU8", "B006YMG92G", "B002EQFXZA", "B001E27DLM", "B000059TMB", "074401543X", "B00C3MKCF6", "B0051U7BZG", "B0013AX2JM", "B001TIFML4", "B000BNMOFU", "B000G7BPOC", "B004CVWETI", "B000UZH7P6", "B002P69VAC", "B0029ZUPSQ", "B0050JN84Q", "B006JKARU8", "B0007V804U", "B000VIUNZI", "B000R3K4CE", "B000HNJ5WE", "B0012FHYS8", "B000G79XQO", "B000QTD05M", "B0010EF0UK", "0804162867", "B00L3LQ4B4", "B002BSC57U", "B00D87TCN8", "B003O8EDUS", "B00B2QL2Y4"], "bought_together": ["B000NPOGWK", "B000NPTOTK"], "buy_after_viewing": ["B000NPTOTK", "B000NPOGWK", "B003YVK5T8", "B000SSPH3E"]}, "salesRank": {"Video Games": 4620}, "categories": [["Video Games", "Kids & Family", "Sony PSP", "Games"], ["Video Games", "Sony PSP", "Games"]]}