{"asin": "B005AY01RI", "description": "Aurum Cables Category 2 Certified High Speed High Speed HDMI Cable with Ethernet - Supports 3D, Audio Return Channel and Up To 4K Resolution* HDMI cable withAUDIO RETURN- combines both audio and video into one cable* Ethernet Channel For Sharing Internet Between HDMI Devices* Compatible with all HDMI DevicesHDMI combines both audio and video into one convenient cable, so it's all you need to connect your HDTV to your A/V receiver, \nBlu-Ray player, Xbox 360, PlayStation 3, HD Cable Box, Personal Computer or any other (High Definition Multimedia Interface) device with an HDMI output.Compatibility- Supports 3D Content- Guaranteed 4Kx2K, 1440p, 1080p, 1080i, 720p, 480p, and 480i Resolutions- Supports Audio Return Channel- Supports Highest Refresh Rates Available- Supports Transfer Rates of Up to 340Mhz or 10.2gbps- Supports True HD Dolby 7.1 and DTS-HD Master Audio- HDCP CompliantQuality Construction- Full Metal Shielding Within Connectors For Durability and Interference Protection- Shielding Throughout Cable- HDMI connectors are 24K Gold plated.Buy With ConfidenceWe at Aurum Cables put tremendous effort in excellence of quality in the cables, we will back our HDMI Cables with a Limited 1-Year Warranty.", "title": "Aurum Ultra Series - High Speed HDMI Cable With Ethernet 10 PACK (2 Ft) - Supports 3D &amp; Audio Return Channel [Latest Version] - 2 Feet - 10 Pack", "price": 29.99, "imUrl": "http://ecx.images-amazon.com/images/I/51KDU2P6OBL._SX300_.jpg", "related": {"also_viewed": ["B009DMFOVG", "B009DLX95U", "B00ELJVM5I", "B009DMI3GY", "B00J2B4J8M", "B00D2ZIRVO", "B00FX6KO8Y", "B00I0ZXN1K", "B00FRK7KTW", "B00HZ2YVXI", "B00GR70UDW", "B00J2E50D2", "B00BEWHOQ6", "B00D2ZCJYA", "B00HZ26N2U", "B00ECEFI7U", "B00DIHW8ZM", "B00DDULUIA", "B006C6IYW2", "B00DIH4F12", "B00HZ2C0BS", "B00EKTMZ7I", "B00FX6ST8G", "B00FQSSWX8", "B00EDOC08Y", "B00BEWF4R2", "B0049PQTLQ", "B00EDNSL6K", "B00A6VSJX8", "B00EDNPIKC", "B00FQT33Q8", "B003JQL0S8", "B00DI88YCC", "B00EV52MB0", "B00I2VJ48S", "B00BEJ83MI", "B00844L4FE", "B00EDO6SG4", "B00EDNXR1E", "B003CT08E4", "B0032FO27M", "B00I2XTN0U", "B00FX9WJNO", "B00EP9YOJ0", "B00ECE9182", "B008D6YZXG", "B00BGBU3X6", "B009DMGASW", "B00DG54ARU", "B00193U3O0", "B003XM1WE0", "B0019EHU8G", "B000HPX46U", "B000JEACFK", "B0049SCB2Y"], "buy_after_viewing": ["B009DMFOVG", "B009DMGASW", "B009DLX95U", "B00DDULUIA"]}, "categories": [["Electronics", "Accessories & Supplies", "Audio & Video Accessories", "Cables & Interconnects", "Video Cables", "HDMI Cables"]]}