{"asin": "B00857SREQ", "related": {"also_bought": ["B00857SRGO", "B00857SRGY", "B00857SR5K", "B00857SRIW", "B004Z20X60", "B004Z20WSE", "B0086FJ4CG", "B004Z20W9I", "B00857SQQU", "B00857SRU0", "B004S5Y8AG", "B004S6E90Y", "B00CTUEPV4", "B00CTJOCQI", "B00CTJOCJK", "B0089WQ6L8", "B004S663OO", "B00CTUER1M", "B008NCTE7W", "B00D8YQRIO", "B00CTJOAB0", "B00CTJOEXO", "B00CXVFX88", "B00CTJOEUM", "B0091IG66O", "B007NLO6B8", "B0050J2G3A", "B007FRHZ4A", "B007RDGH5U", "B004RKT8U2", "B00DMEEYSK", "B00CTJOETS", "B00CTJOGKA", "B0083F31JG", "B007VD4G3Q", "B00DS9TLG4", "B005GBRMMM", "B004RQ64Q2", "B005NJSVM2", "B005GVWI76", "B00CTJOGIW", "B004VUX5XO", "B0087HU37S", "B0050SVGJG", "B00GJ9RF6I", "B003I4L9PK", "B006MVE3UY", "B007X1835I", "B007RDFMTM", "B007S3S7IO", "B002WJI64E", "B004RKTA9Q", "B005JR5PNQ", "B005LAIH4A", "B001DU5GNM", "B004OFBJX4", "B0083F31IW", "B004GTMB2G", "B0053BCMAC", "075669812X", "B0085TZRME", "B007R6U53C", "B004RKP35Q", "B00659T3F8", "B0090HDMW2", "B0085TZRMY", "B007UDYTLG", "B004RJ5A3M", "B003BLQDWE", "B005JR5V8A", "B0089MQW94", "B002WJI65S", "B008SBZE6S", "B005JR5SYM", "B0083F31JQ", "B0090GWSZU", "B000F1ST1Q", "B00CXWASCI", "B007R9P2I2", "B004QXY4ZE", "B004XNFKFK", "B00EJOCB4G", "B004MOWBV6", "B007R9P2OG", "B0090GWSWS", "B007NLO6IG", "B004SKLU4I", "B005JR5QFI", "B0052J893E", "1423124235", "B00J5B0V2C", "B000BPAIT2", "B00168PI9S", "B005PMMN9E", "B004ZX141C", "B007CJK05C", "B008RWVE8A", "B0098EVZZ8"], "also_viewed": ["B004Z20X60", "B00857SRU0", "B004S5Y8AG", "B00857SRIW", "B00CTUEPV4", "B00857SRGO", "B005NJSVM2", "B004S663OO", "B00D8YQRIO", "B00857SRGY", "B0089WQ6L8", "B0091IG66O", "B00CTJOCJK", "B00DS9TLG4", "B00857SR5K", "B00CTJOCQI", "B004S6E90Y", "B00CTJOETS", "B00DMEEYSK", "B005GBRMMM", "B00CTUER1M", "B004Z20WSE", "B00CTJOEXO", "B005GVWI76", "B00CXVFX88", "B00D43F77Q", "B00DS9TLY6", "B00CTJOAB0", "B00GJ9RF6I", "B00857SQQU", "B007VD4G3Q", "B004Z20W9I", "B00CTJOGIW", "B008NCTE7W", "B0050J2G3A", "B005GBPDHI", "B00IFVH0ZY", "B00GPV1UIE", "B005W67B6S", "B00FA341QG", "B006MKXNW4", "B00CTJOGKA", "B003I4L9PK", "B005XO71S2", "B00CTJOEUM", "B00FA341O8", "B004S64292", "B00EGY6KBO", "B00HROBO7A", "B00BZR5WG4", "B00IFVH0NQ", "B00CXWASCI", "B005KBUMXY", "B0086FJ4CG", "B00IKIXCWM", "B00FA341XO", "B007RZ7DWY", "B00FA342SI", "B00BGYO5CS", "B00I0DOB22"], "bought_together": ["B00857SRGO", "B00857SRGY"]}, "title": "Nintendo Mario and Bowsers Ice Race Building Set", "price": 21.85, "salesRank": {"Toys & Games": 24885}, "imUrl": "http://ecx.images-amazon.com/images/I/51lzxvNXv6L._SX300_.jpg", "brand": "Nintendo", "categories": [["Toys & Games", "Building Toys", "Building Sets"]], "description": ""}