{"asin": "B003UT2E8E", "categories": [["Electronics", "Computers & Accessories", "Cables & Accessories", "Keyboards"]], "description": "", "title": "Microsoft Wired Keyboard 200 (Black)", "price": 14.23, "imUrl": "http://ecx.images-amazon.com/images/I/41XdRMvP4qL._SX300_.jpg", "brand": "Microsoft", "related": {"also_bought": ["B005058AE8", "B009SPWCFY", "B003FOWIXK", "B003L62T7W", "B002ZIN9DU", "B002FYL7PG", "B0033Z2BAQ", "B001OAR26K", "B005EJH6RW", "B00CAJNY16", "B0088PUEPK", "B003B4BBFK", "B00081N53K", "B00902BFGC", "B005BZNDOO", "B006YG8ZNI", "B009SPWJ98", "B002YIG9AQ", "B00G5TDGK6", "B002DPUUL4", "B000R9AAJA", "B005T3GRNW", "B004EMSH9Q", "B00006B8EC", "B00J8E8YES", "B00J2LIF2S", "B003M0NURK", "B00E3W1726", "B0098Y77U0", "B00H09BOXQ", "B00J2LIFBY", "B004V94F5C", "B00DJCB83O", "B000AOYWVE", "B0017KE3DM", "B00BBLG75Y", "B00B7GV802", "B005LJWJSG", "B007TTEHUY", "B00EUAFAF6", "B004IZN3K2", "B008P9YIGA", "B00HB77YRW", "B008JJLW4M", "B00COGDERY", "B003ELVLKU", "B00ECDM78E", "B00BP5KOPA", "B000UD4LIY", "B005058AGQ", "B0092ML1SC", "B005J7Y7TY", "B0036VO632", "B00DESAOV0", "B004G3WCLM", "B003HE260I", "B006TVQU6C", "B001QUA6RA", "B00EMHM622", "B0000AI0N1", "B002UOR17Y", "B00AGQ4WHA", "B003CP0OT2", "B00F3ZN0CC", "B006YG9EEW", "B00C2DLI9A", "B005CT56R6", "B000HLZXH2", "B00FJRS628", "B005BZNDS0", "B0092ML0MY", "B00E3W19MO", "B005EOWBHC", "B007B5YUMQ", "B004SUO1R6", "B00EPRCZ16", "B002B3YCQM", "B005JN9310", "B003NREDC8", "B00DHW4HXY", "B00D601UC8", "B00CO8TA4I", "B0057Q4ADU", "B00GAKX34E", "B009O7YU56", "B00FE29IWK", "B0007MWE1E", "B000A6PPOK", "B007ZW2LY4", "B004C9O6T6", "B00F3ZN2W0", "B003NR57BY", "B00007AP2O", "B00D1A5OR0", "B0049MPQA4", "B00H09BB16", "B00B3P1IGG", "B00461G3MS"], "bought_together": ["B005058AE8", "B005EJH6RW"], "buy_after_viewing": ["B003ELVLKU", "B005EOWBHC", "B00BP5KOPA", "B001OAR26K"]}}