{"asin": "B002FFT8Z6", "related": {"also_bought": ["B007S642BW", "B007MHFMMU", "B00274NRRA", "B0010HE6LG", "B00529F3JW", "B004CQGAYS", "B004I1GHY0", "B003SWLRLS", "B0002AKX6Y", "B002FFZGCU", "B00BWF5U0M", "B006B3PADC", "B002AH8T3Q", "B007T4RL5C", "B003AVGN5M", "B00EOT2HWM", "B000VJG356", "B003C2T08G", "B0018LO1R8", "B0027C8M8G", "B00182CIB8", "B000NTEHM0", "B006DUDWXI", "B00D2ZHO2C", "B003D15K44", "B002WLHPNK", "B004AUK9IY", "B001B077PO", "B00CS99VSS", "B001VHO5LQ", "B00E5ZE00C", "B0049ME3BM", "B003QH2MY6", "B0015TJNEY", "B004L37VFE", "B000N35A0Y", "B0092RUJZS", "B004FRJULY", "B00BJ6XZEM", "B00475WJEY", "B005DUX5CM", "B00EV5GZ5E", "B00JB257XS", "B007DVM39A", "B00CHXAV1Q", "B00AG1T5MM", "B0032GU1LW", "B0032R6CPK", "B004GWBHNM", "B0028Y4F4S", "B005HZZA80", "B007K8EDI0", "B006W5MQCM", "B005GRSQDK", "B00A64SIXQ", "B002670LY0", "9573212919", "B002JF8PS8", "B002782LTG", "B0084V5FD4", "B00BJOZNV2", "B006LSQW4I", "B005QX7KYU", "B0027EMHM6", "B00BPHBCX6", "B007HISGRW", "B00CXAC1ZW", "B002WLOSSA", "B0050PUGZE", "B003VX3S3Y", "B00BS67S78", "B001GC9C9Q", "B005NG71K8", "B001J226JQ", "B001TH7GUU", "B00B9996LA", "B009FA2UYK", "B003L137Y6", "B002EQ6E9E", "B00802O1JQ", "B004WIOOI0", "6073894996", "B00C20FV78", "B000BSN4UY", "B00466887G", "B00E88ZGNG", "B008295PTC", "B00DJUU0KS", "B00DXZKYTQ", "B008279OJ6", "B001CEY392", "B004CFDJ2A", "B005HKIDF2", "B00BP5KOPA", "B0016LC5VY", "B00DR0RBV6", "B004I53ZX2", "B00GGM0Y66", "B001E3ZM8M"], "bought_together": ["B007S642BW", "B007MHFMMU"], "buy_after_viewing": ["B00BWF5U0M", "B007S642BW", "B003M0NURK", "B007MHFMMU"]}, "title": "Black 4-Port High Speed USB 2.0 Hub", "price": 2.27, "salesRank": {}, "imUrl": "http://ecx.images-amazon.com/images/I/419uuD-RjHL._SY300_.jpg", "brand": "GTMax", "categories": [["Electronics", "Computers & Accessories", "Cables & Accessories", "Cables & Interconnects", "USB Cables"]], "description": "Brand New GTMax accessories.This 4 port USB hub is the ideal companion for laptop or desktop computer.Octopus extension is great for bulky USB devices like thumb drives that won't work with standard hubsxGreat on laptops with hard to reach USB portsIdeal USB expansion for portable use on the road or at home.Perfect for connecting USB 1.1 or 2.0 peripherals such as USB mice, USB Portable Hard Drives, USB CD-R/RW or DVD-ROM drives and USB 1.1 hubs!Allows simultaneous operation of up to four separate devices all attached to a single USB port.Plug and PlaySupports Windows Vista, Windows XP, 2000, 98, and Mac OS 8.6 and higherCompatibility: Compatible with all PC/Laptop with USB portUPC Code:088515701773"}