{"asin": "B00GLS593S", "related": {"also_bought": ["B00GLS58SO", "B00GLS554Q", "B00GLS55DC", "B0012UEJ1S", "B00FYSZDPK", "B00GLS58OS", "B005SHT1KK", "B005MIFIW0", "B00GLS5DCU", "B001ET79AK", "B006OHM6FK", "B00CP4HMCS", "B00JRP86A0", "B00GTBZ7R0", "B00JRPLEZE", "B000P9B3R0", "B005MIFIWK", "B00JNUF1PC", "B00DBEAAMA", "B00ILWBLUM", "B005CYJY9C", "B0088W8NTW", "B00K2T5XEC", "B00D8PT9FQ", "B008JAPA7Q", "B004K3D0FK", "B00JNXOJAC", "B0016P2JWU", "B002PMLGVI", "B004GIH1UO", "B00AQX87M4", "B008FVQNSE", "B00ID4RCLK", "B004H4VQ4Y", "B004ECF7LC", "B0081RZ2X4", "B002RS6KU2"], "also_viewed": ["B00GLS58SO", "B00GLS554Q", "B000P9B3R0", "B0012UEJ1S", "B00GLS58OS", "B00GLS55DC", "B001ET79AK", "B00GLS5938", "B000GCZZZC", "B005SHT1KK", "B001L7MZKY", "B005CYJY9C", "B00KACGQZ6", "B007RZLNHK", "B005MIFIW0", "B004DK5CUQ", "B00AFWKAN0", "B005K95ZVA", "B006OHM6FK", "B000KOWCXE", "B00K8EQLLA", "B00GLS592E", "B005MIFIWK", "B00GTBZ7R0", "B00FMJFZZY", "B00K2T5XEC", "B000OR3UWO", "B001CX3ZVU", "B001AZXEHU", "B003RW7498", "B00HFMS2I8", "B00J15HNRI", "B00JRP86A0", "B00JU9K6FQ", "B002PMLGVI", "B004LGX73Q", "B00BEY383C", "B001SR3M1S", "B00GM9XT7E", "B00A7760R8", "B004J6E6NS", "B00JRQ2DPI", "B000P9BRG2", "B00BCEGKI4", "B003N789UK", "B00J2HTFG2", "B004ECBW34", "B00ACLI7XY", "B001BAFQMK", "B004K3D0FK", "B004DK8X1G", "B00KH6VT5M", "B001IY03G8", "B002COEWEW"], "bought_together": ["B00GLS58SO"]}, "title": "John Frieda Precision Foam Hair Color, Glosser Warm Blonde, 6 Fluid Ounce", "price": 9.99, "salesRank": {"Beauty": 16105}, "imUrl": "http://ecx.images-amazon.com/images/I/31YhA30igtL._SY300_.jpg", "brand": "John Frieda", "categories": [["Beauty", "Hair Care", "Hair Color", "Highlights"]], "description": "An in-shower, non-damaging weekly color extending treatment that adds back lost color pigments for true to tone, salon-fresh color in-between colorings. Instantly restore vibrant salon-fresh color and shine. Adds golden tones to freshen blonde. An in-shower non-damaging weekly color extending treatment that adds back lost color pigments. Delivers true to tone salon-fresh color in-between colorings."}