{"asin": "B00004ZC8Y", "related": {"also_bought": ["B000BTYEHA", "B00004ZCJE", "B00004ZC92", "B0000BZL1P", "B0057LX9H8", "B00IAS60VM", "B0055N2L22", "B0043VE29C", "B00DJS830Y", "B00HWMP0XG", "B0000AI1EC", "B002IKLJVE", "B0096WDK0K", "B0085J3THO", "B0084FM5JC", "B00I19TVU2", "B0083WYFWG", "B00I9GYG8O", "B00CI3R53W", "B00603S0CG", "B00E87OITK", "B00EEA960W", "B00CI3R4VU", "B00F7L454E", "B0054EPPZM", "B00009KLAD", "B005TOU804", "B0058PL9R0", "B0090CFY1E", "B002LARVXQ", "B00009UTCK", "B005J5TZWK", "B00EHJNASY", "B00B02FXJU", "B00CMRTVFE", "B000A1SVXC", "B0048IH5EY", "B0071UHPTQ", "B007SK9GCS", "B003Y2WUJ0", "B0061GS1OO", "B00009R96B", "B007EZGOMC", "B00E87OK84", "B00ICMNE7O", "B0083WYGC0", "B005NJCFRE", "B00BUXERJQ", "B0058PL9QG", "B001ISKNKA", "B0051QL7E6", "B002KDVQXU", "B00CSU5Q5O", "B009DL0LOW", "B0000AIS1T", "B00604YTFM", "B0043RTLNI", "B00G0J3FRK", "B00EEA925G", "B00J3KA814", "B009I5E9QY", "B00J47MOYU", "B003150B6O", "B004OI0NGK", "B009SGB3KS", "B003USTMHG", "B00BQXL5CM", "B00EN01Y44", "B00BPWDAH2", "B00009KLAF", "B001G41Y1S", "B009KG77D8", "B005AIR2TE", "B0066J6EOU", "B004LO7WGG", "B00111Y292", "B002CGSYOO", "B005KK40ZQ", "B0081RN9YI", "B0049IOPFK", "B00AWVB4R0", "B004LO5KHO", "B00EQ07PG2", "B00INBP6V6", "B00IVPU6AU", "B00A7Q9U9Y", "B00CI3TQSO", "B0074WDGAI", "B00603RU18", "B00HQPF7PU", "B00836JHVQ", "B00G5ZCFRA", "B00BPZD0M4", "B0043VE28S", "B00CFCTDD6"], "bought_together": ["B00004ZCJE"], "buy_after_viewing": ["B000BTYEHA", "B00004ZCJE", "B0000BZL1P", "B009WDGTGK"]}, "title": "Tiffen 46mm Circular Polarizer", "price": 17.2, "salesRank": {}, "imUrl": "http://ecx.images-amazon.com/images/I/41IFdDLyomL._SY300_.jpg", "brand": "Tiffen", "categories": [["Electronics", "Camera & Photo", "Accessories", "Filters & Accessories", "Polarizing Filters"]], "description": "A circular polarizer has the same effect as a polarizer and is used on  cameras with beam-splitting metering systems commonly found on autofocus SLRs."}