{"asin": "B0057G2TH4", "related": {"also_bought": ["B002KEYYF6", "B00004ZCJK", "B0029LH3TE", "B001UE6N88", "B004L7X5KU", "B00BAF0I06", "B009B0MZ1M", "B00004ZCFQ", "B004RAQVY8", "B0065MMKTG", "B00494QFBG", "B00AT74VOU", "B00494X5VO", "B005WXQO3W", "B0044BYKI4", "B0061ZP01M", "B00009PZX6", "B0064T1D3O", "B001KN766W", "B00A2BWAY6", "B004PJJU30", "B00DWIAVWY", "B00603S04E", "B0064Q4GEA", "B00004WCID", "B007RN5WDI", "B006ZCCH76", "B00C1PXJ8W", "B00DVPG9JW", "B002L77LQQ", "B006JOX2HO", "B00C699L30", "B00AAGBJGI", "B00AA48DVO", "B00FWFPHH4", "B006JPNGRE", "B00461J0J6", "B00BMXG6DE", "B0083WGXTO", "B009Y68R0Q", "B0066WEGEC", "B00603RV9O", "B00603RW70", "B0029LH402", "B00C9IHUY0", "B009NLU80Y", "B0039BPG1A", "B00C9L6JYY", "B00DZIFWSO", "B007X5AGXG", "B00DZ0SMY8", "B00AGI5W5E", "B006ZNBILG", "B00603RZ9K", "B008YCNPLM", "B009Y68QIY", "B009SX9YJI", "B002K4GDGY", "B007SXJ13E", "B00BGGRTMO", "B005MTMFHU", "B00BMXH25U", "B0000BZL8H", "B0083WYE0E", "B00004ZCFZ", "B005C4Z4CI", "B0059AK8HQ", "B00603RW4S", "B0062AYFWG", "B000KL5T9G", "B009TDGJJK", "B009W50ZJ0", "B00009R6KN", "B004F3OYQ4", "B0065MMK8W", "B0055I2JWO", "B00C9L6N5O", "B005WXI3H2", "B005V2GENY", "B003VNKNF0", "B003WCYTQO", "B002DVWN18", "B0083WYFWG", "B0037T3634", "B009IY72OQ", "B0083WYC9W", "B008WNN3I8", "B0083WYAIA", "B0000AQ58U", "B009ITLRII", "B009YTVEB2", "B004MLF4ZO", "B0000TQABY", "B00DNET8HG", "B0002HMRJS", "B0046V0VNA", "B007W544GM"], "bought_together": ["B00004ZCJK", "B00004ZCFQ"], "buy_after_viewing": ["B00C9L6JYY", "B00494X5VO", "B00C699L30", "B004MLF4ZO"]}, "title": "Bower FA-DC67A Ring Adapter Tube for Canon PowerShot SX30 IS, SX40 HS &amp; SH50 HS Digital Camera (67mm)", "price": 8.92, "salesRank": {}, "imUrl": "http://ecx.images-amazon.com/images/I/412SQ%2BlzvkL._SY300_.jpg", "brand": "Bower", "categories": [["Electronics", "Camera & Photo", "Accessories", "Lens Accessories", "Adapters & Converters"]], "description": "Thisadapter ringprovides a67mmthreaded mount for adding telephoto and wide angle lenses or filters to the front of your compatible Canon PowerShot digital camera. Attaches via bayonet mount."}