{"asin": "B00009RA60", "related": {"also_bought": ["B00009RA5Z", "B0007P11M4", "B0000512LA", "B00009MDBU", "B00FBJ5O7Y", "B0000514G8", "B0019804U8", "B00DVH64HW", "B0038ZTZ3W", "B0002WYJSU", "B002U729UA", "B00A4K04XE", "B00305K3E0", "B00009KYCN", "B008X3JHJQ", "B00DI89I04", "B00C2DLRV4", "B003Y24DEU", "B006C2DV5G", "B0001FTVD6", "B005DL2OVE", "B0000513O4", "B005ZTJ980", "B001E1Y5O6", "B000QZ3UG0", "B000Z80ICM", "B0000511U7", "B00077INZU", "B0012YLTR6", "B000BKUSS8", "B002BH3Z8E", "B0012YFXSW", "B004XXMUCQ", "B002D0DK8E", "B007ED8EXG", "B005STXPX2", "B00006RVPW", "B0007OGTGS", "B005BZNDOO", "B00AJHBBOI", "B00E3W19MO", "B001985SWW", "B002N6F2UW", "B0098R0600", "B004U4WYLU", "B00004YOHP", "B002MUYOLW", "B000RGF29Q", "B00GTGETFG", "B003BQ91Y6", "B009SQQF9C", "B000N99BBC", "B005CY100I", "B000BSN1TS", "B0089OORW6", "B000J2EN4S", "B006M1MFEA", "B00006B81E", "B0068LACFI", "B0002CWPW2", "B0006Q4AV8", "B00C2CA3N8", "B000784H4K", "B0000BVYT3", "B0052SCU8U", "B000UD4LIY", "B00939KFOU", "B00EHBEUZO", "B00EHBERSE", "B00E3W1726", "B009UOIAEU", "B009TZTGWK", "B003VAGXZC", "B005T3GRNW", "B00ASJRMT0", "B00BQ8RM1A", "B00H09BOXQ", "B003YFHCKY", "B00BP5KOPA", "B005EORRBW", "B00D601UC8"], "bought_together": ["B00009MDBU"], "buy_after_viewing": ["B0007P11M4", "B0000514G8", "B00006B81D", "B00009RA5Z"]}, "title": "APC LE1200 Line-R 1200VA Automatic Voltage Regulator", "price": 57.44, "salesRank": {}, "imUrl": "http://ecx.images-amazon.com/images/I/41pjo-Ze8cL._SY300_.jpg", "brand": "APC", "categories": [["Electronics", "Computers & Accessories", "Cables & Accessories", "Surge Protectors"]], "description": "Automatic voltage regulation for protection against brownouts and overvoltages.---Automatic Voltage Regulation (AVR).---Brownout correction.---Overvoltage Correction.---Power Cord.---Status Indicator LEDs.---Surge Protection."}