{"asin": "B00CTUFWA2", "categories": [["Toys & Games", "Building Toys", "Building Sets"]], "description": "Go back to the railroad days and build a railway &#x2013; lay the rails, drive the engine, stop at the junction. Lincoln Logs Redwood Junction has 235 pieces including real wood logs, railroad track, 3-piece train engine, colorful figures and other building accessories. Step-by-step instructions for building the train track, junction stations and more.", "title": "Lincoln Logs Redwood Junction - Amazon Exclusive", "price": 65.67, "salesRank": {"Toys & Games": 8604}, "imUrl": "http://ecx.images-amazon.com/images/I/512YEuc8aFL._SX300_.jpg", "related": {"also_bought": ["B00AASUNMC", "B003MGJTDI", "B008UH9NA8", "B004S6EHFQ", "B009L91XUM", "B002Q826EW", "B00000IV4K", "B004IJC60Q", "B004S6A0TI", "B00IE3EF06", "B00857SRSW", "B004EZHZCI", "B009IVP4OE", "1402750773", "B007B288FO", "B003CYBFEG", "B009IX2GTS", "B00CTUEQF4", "B000F9X792", "B00CTJOGOG", "B000BYPZIM", "B00B1HH144", "B004P5O8MC", "B00GVD45NS", "B00A850SFO", "B000096QQ1", "B0050DZEVM", "B000N5QNSK", "B00000DMCE", "B0037UT3E4", "B00B5I7G3A", "B000CBSNRY", "0800788222", "B002V7YBNC", "B00F2MQ0GO", "B0007Y4DLG", "0803736800", "B00000JIVS", "B00006JZCG", "0972394648", "1450805752", "B000H1IYXW", "B00AWBLS80", "B000NO9GT4", "B00GSPFCX6", "B00CQHZ12W"], "also_viewed": ["B003MGJTDI", "B00AASUNMC", "B004S6EHFQ", "B007B288FO", "B004IJC60Q", "B00000IV4K", "B009L91XUM", "B004EZHZCI", "B008UH9NA8", "B004S6A0TI", "B002Q826EW", "B003CYBFEG", "B00588UFM2", "B001721YFA", "B007B2883G", "B00000IUYM", "B003NTPGTK", "B0006MZNU4", "B000A10Z7M", "B000063S5X", "B000XP3WUC", "B00769PN1O", "B004EZPFE8", "B00GP038SU", "B00CTJOGOG", "B002ONVBFO", "B007B2889U", "B00005O7NR", "B0007OAPHC", "B009M66HXM", "B00171YA3E", "B000S6A0G0", "B002PD8R6Y", "B00857SRSW", "B00CTUEQF4", "B00000IUYL", "B00769QM0A", "B001G4BRE2", "B000GGY5VI", "1402750773", "B00B1HH144", "B000BN8YAO", "B000O9GR8Q", "B00K00QNPG", "B001EHBJTE", "B009IVP4OE", "B0009VCVCU", "B004HQP1QG", "B000AEOFFM", "B00CTUEQ68", "B000BYPZIM"], "bought_together": ["B003MGJTDI", "B00AASUNMC"]}}