{"asin": "B007WFZ0XI", "categories": [["Beauty", "Skin Care", "Body", "Moisturizers", "Oils"]], "description": "Quality: 100% Pure, First Cold Pressed Raw & Organic Ultra Premium Grade - Certification : USDA Certified Organic Oil- Ingredients: 100% Argania Spinosa. Farming Methods : Organic & Sustainable Farming -FAIR TRADE: Yes, Ethically Sourced through Fair Trade and Women's Co-Ops & Organic  Sustainable Farming.Comes in a beautiful frosted amber glass bottle with a very nice &  stylish Treatment Pump & is packed in a nice organic & rustic Box with a USDA Certificate of Authenticity. You will absolutely love the Excellent Quality of this Premium Grade Organic Argan Oil. Perfect for personal use, family & gifts.\n100% Satisfaction Guarantee & Unconditional Hassle Free 90 Days Return Policy ( no questions asked )", "title": "Savanaah's Organic Argan Oil 4 Oz / 120 ML 100% Pure &amp; Cold Pressed -Ultra Premium Quality", "price": 24.95, "salesRank": {"Beauty": 34060}, "imUrl": "http://ecx.images-amazon.com/images/I/51ESsape%2BDL._SY300_.jpg", "related": {"also_bought": ["B00BNZNG66", "B004Z209HS", "B0015Z5BU8", "B00066D4M4", "B000NRX660", "B001E763CW", "B00H93NJLS", "B00JMBDZGO", "B0051BWV28", "B005H37238", "B004S2G4FG", "B0015YSNUE", "B00EGOX98G", "B001ECQ41M", "B005SUN1SK", "B00IP42FBA", "B006ZAW0K2", "B004MAO6NQ", "B004RZF1SK", "B006WQ2SUQ", "B00CX1TG40", "B006GNZ3KM", "B003XKY57S", "B00GJYQCB2", "B00502NMTE", "B006YUOHXQ", "0874835631", "B00CJGRYMU", "B00CHMWAY8", "B00D3M0CRS", "B0016B5OEO", "B005Z49KSY", "B0047AKVW6", "B00GDLXS5E", "B003ZJ5S28", "B009D6ZLR4", "B00C7DYBX0", "B00GZ0WFQG", "B001G2PEBG", "B0051BXA1Y", "B00KYVPI7U", "B003E1H27Q", "B00FAU2QCU", "B00CPX2FLM", "B0010ED34U", "B002Z45SD8", "B0019LTGOU", "B00GJX58PE", "B00AXKU7MI", "B000VSZDVW", "B00608S5EY", "B00JVXVBQE", "B00KDIONMK", "B006Z9ACMG", "B005P0WRLU", "B00LP21ARO", "B0016BBWZO", "B000ELP5KA", "B009JVQRU8", "B00CME22DK", "B00E9VZC4U", "B001MX89Y8", "B00B7MUJR4", "B0032RPLSY", "B009AH7OU8", "B005KG7EDU", "B004BL2DHC", "B001EO5Q64", "B001UE60E0", "B004E79EQQ", "B00G052NFE", "B00D9NV1NU", "B00G5V6VYW", "B000GAO91K", "B0008D6WBA", "B0016BJQN4"], "also_viewed": ["B004Z209HS", "B00BNZNG66", "B00H93NJLS", "B000NRX660", "B0015Z5BU8", "B0013LUPQY", "B004S2G4FG", "B00GZLTD2Y", "B003XKY57S", "B00066D4M4", "B0015YSNUE", "B005H37238", "B00GMAWI66", "B0006SFXXK", "B00H7NKNE6", "B00IT1HKV4", "B00CJGRYMU", "B00GJYQCB2", "B00C0HF1J6", "B009D6ZQCO", "B00B7ZFMA0", "B00G5WO2R4", "B00I134Y82", "B00KGCAK4S", "B00EO5G3FS", "B007CDSFKU", "B000VSZDVW", "B00D3M0CRS", "B004HYEZ06", "B00GDLXS5E", "B00CX1TG40", "B00H8YF1VE", "B000Z915L4", "B004S2FY7K", "B00GSMJG36", "B001E763CW", "B001V9LUYO", "B00JMBDKP0", "B00EABZTBU", "B00L5JHZJO", "B00E9VZC4U", "B000E3FIW8", "B00D5KVDOE", "B007SIG5HY", "B00JMBDZGO", "B001ECQ41M", "B0027IS1O0", "B00H416L6U", "B00EGOX98G", "B001E77NSU", "B001DJ9JJU", "B002UJ31HS", "B005P0WRLU", "B005C1741A", "B0000532YN", "B004RZF1SK", "B00FRI8MLE"], "bought_together": ["B004Z209HS"]}}