{"asin": "B00006HSYC", "categories": [["Electronics", "Computers & Accessories", "Networking Products", "Network Adapters"]], "description": "To link several line cords together, or extend modular cable runs, this modular coupler can help you make the right connection. This inline coupler provides a female-to-female feed-through connection for easy cable hookup. Use for data/PBX applications.", "title": "Cables to Go RJ45 8-pin Modular Inline Coupler Straight Through, Ivory (01937)", "price": 1.19, "imUrl": "http://ecx.images-amazon.com/images/I/41c7d8Z6%2BkL._SY300_.jpg", "brand": "C2G", "related": {"also_bought": ["B003C2QS90", "B000BSLW8U", "B003C2YOE6", "B0034XBFJU", "B00000JDF5", "B000E8DMU8", "B0051D9XT0", "B00000J1V5", "B00337FY76", "B0016897GS", "B003IYS8SQ", "B000E8BGCE", "B000FNFSPY", "B00004Z5H3", "B000TYR5R8", "B002HK0UQK", "B004V7LSAO", "B000I97FHY", "B004713JLU", "B002MSHMI6", "B001TH7GVE", "B001SIGXHC", "B001W28L2Y", "B001TH7GVO", "B0000AZK4G", "B00005V51P", "B00B2GD29M", "B000I20AJ6", "B00288Z0Q6", "B0018EF3IG", "B001W26TIW", "B000P1OA1O", "B00APOPDSA", "B008UY5WL0", "B00002EQCW", "B004MU241C", "B001QUA6RA", "B0036H22TG", "B00256HWRG", "B00EUHRLF6", "B004717WGI", "B00939KFOU", "B005D7I27I", "B000V1R96Q", "B003EE12EC", "B00EEJHEU2", "B000I94F3G", "B008P731L0", "B000QZ001I", "B002HFO8JA", "B00426HLQO", "B002HK867A", "B001DBIT08", "B009AFW6XU", "B00G7GMEOG", "B002EP30EM", "B0000BVYT3", "B003RCEAB8", "B00004Z5MG", "B0055EXMII", "B00004Z5P4", "B0086SQDMM", "B00I8V97DY", "B00B1GQ0CO", "B0034XRLGQ", "B001EPVOQY", "B003O9FZUY", "B00DR0QT5U", "B000I21Z5E", "B0020Z8PBY", "B000067RH5", "B000N99BBC", "B003V70LYE", "B003RCI4OW", "B000067RTI", "B00CJHXY0U", "B00B3UT5JI", "B00006RVPW", "B004I0JGT4", "B002A6CWCQ", "B0094D51IU", "B00E5I7UAG", "B003LD1P8O", "B00FQMKZU2", "B000FI9VU2", "B006OIDURW", "B003RCI5A0", "B0034CSUZ8", "B0015V1H28", "B0002J1TUO", "B00B3X4NM4", "B00870ZHCQ", "B005LS2J14", "B00466OO4C", "B001TH7GUU", "B000KMFDZ0", "B001W26TKU"], "bought_together": ["B000BSLW8U", "B003C2QS90"], "buy_after_viewing": ["B000BSLW8U", "B001SIGXHC", "B00FQMKZU2", "B00EQ5SQM4"]}}