{"asin": "B00CO089XO", "categories": [["Electronics", "Camera & Photo", "Bags & Cases", "Camera Cases"]], "description": "This \"sport\" sling offers the enthusiast photographer an outdoor-friendly and durable with rip stop nylon, zippered outer pockets and thick webbing straps. Its multi-use design includes a removable camera box to fit a CSC or DSLR, plus extras.", "title": "Lowepro LP36572-0WW Photo Sport Shoulder 12L (Purple/Grey)", "price": 74.99, "imUrl": "http://ecx.images-amazon.com/images/I/41DFr5%2BY6IL._SY300_.jpg", "brand": "Lowepro", "related": {"also_viewed": ["B0039NLS4C", "B0039NLS3I", "B00CO089X4", "B009H2LZQ0", "B00J8V1INU", "B00J938IWG", "B009GYIKHQ", "B00CVS1GJS", "B00HFKKDKU", "B00BDC86NC", "B009GA6BXK", "B009GA6BTY", "B00DFVQCLW", "B007I5B3EW", "B00F5JH64E", "B00F5JH6A8", "B009GA6CXO", "B009ERIVZG", "B00D6631W4", "B0039NLS4W", "B002ISXBFI", "B00D96LZ6K", "B007G96YAS", "B0077B3E5S", "B00GJ928SI", "B00DEH5XPS", "B0037NZ9W6", "B00F5JHA4A", "B00BVQXG3U", "B009M3UQ78", "B007Q5HYMY", "B00F5JHAK4", "B002P3KY7Y", "B005AYK466", "B00AE0O1D8", "B00452UXG0", "B00BVQXG4Y", "B00IG2SJF2", "B000AEEXUE", "B00452UXEW", "B002P3KY7E", "B00EYS1GFC", "B001H33VSM", "B00BIK0524", "B003656Q7C", "B0077B2XI2", "B00CHPQ1T0", "B000P41DZM", "B0077B403S", "B009GYIJ3Q", "B009HPC228", "B009GA6CNY", "B005VTIMEQ", "B0092PNHIG", "B000P3ZB42", "B002BH3XXQ", "B0028XD0EU", "B009M3UQ5K", "B003658PH6"], "bought_together": ["B00004ZCJI"], "buy_after_viewing": ["B0039NLS4C", "B0039NLS3I", "B00CO089X4", "B00CO089X4", "B009H2LZQ0"]}}