{"asin": "B0009WPZM2", "description": "The Godfather puts you into the action of the legendary films, while you relive the classic moments of the Corleone family. After a life of small-time jobs and petty thefts, you are accepted into the Corleone family -- America's most famous criminal organization. It will be up to you to carry out orders, earn respect and make New York City your own. Featuring the voices of James Caan and Robert Duvall and the likeness of Marlon Brando.", "price": 27.99, "imUrl": "http://ecx.images-amazon.com/images/I/4118JBY1T6L._SY300_.jpg", "related": {"also_bought": ["B001GJ306U", "B000ZK698C", "B001RTCOWK", "B002I0HBZW", "B0007PLKZW", "B007PKSNDO", "B000930DLY", "0761553681", "B000083GIV", "B0076ZPYPI", "B00149ILCK", "B0009Z3I0A", "B0023CBY4E", "B003O6N2TI", "B000GPVUOY", "0804162972", "B000UUFQZE", "B002I0K50U", "B000KGD1GO", "B001L18RIE", "B0022TNO7S", "B0007PLKZM", "B00F3F2XAW", "B00BMFIXT2", "B005DKMC6M", "B004EW7LSY", "B000PE0HBS", "B0065FYG8G", "B005FDUSTA", "B000FRU1UM", "B0087Y3M5G", "B00AA4FDT4", "B003S2MXRA", "B0086V5V9A", "B000QCU9I0", "B005FYK2PO", "B000BLM5PG", "B0050SY9WC", "B005N4HBE6", "B00354NAYG", "B0014G98WA", "B004QEV0MI", "B004CVQUGQ", "B000GV4JQE", "B000SH3XD6", "B000FZZ5UA", "B0050SYILE", "B00886WO5W", "B0008JILX6", "B003VKLABE", "B000ZKDOV2", "B0050SY5BM", "B003DZ4F64", "B00BRQN2EM", "B0013RATNM", "B001AWIP68", "B003P9C6QY", "B0010AYJXI", "B00309U0M6", "B0050SYLRK", "B000X1PE16", "B008XMSRKC", "B00EVWZHLK", "B0050SYV70", "B005THAX5Q", "B007SRM5MO", "B0050SYW1U", "B001SH7YMG", "B007V9NHM6", "B008E6ZXT0", "B0053BSNZU", "B001P2M532", "B001REZLY8", "B00008DHNN", "B0085CA8NY", "B000P46NMK", "B0045EI7I4", "B008E6ZXRM", "B007Z3UUF0", "B00BRQP2C2", "B00G9DFLP6", "B000N60GV4", "B000RHZ9JI", "B003C1I0CO", "B003O6CA64", "B001GGO1GG", "B003Q53VZC", "B005C2D2MO", "B00EW47602", "B000FBMITA", "B000WPXQSQ", "B001CRQYBO", "B0056WJA30", "B005EZ5GQY", "B00CPKUV7K", "B005VBVQAG", "B003L8HQ7S", "B002I098JE", "B0050SY77E"], "bought_together": ["B001GJ306U", "B000ZK698C"], "buy_after_viewing": ["B001GJ306U", "B000ZK698C", "B002I0HBZW", "B0022TNO7S"]}, "salesRank": {"Video Games": 3209}, "categories": [["Video Games", "Xbox 360", "Games"]]}