{"asin": "B000O7WFHA", "categories": [["Electronics", "Accessories & Supplies", "Audio & Video Accessories", "Cables & Interconnects", "Power Cables"]], "description": "This 4 Pin P4 CPU Power Extension Cable extends the reach of your ATX12V power supply CPU power connector by 8in, making it easier to make the necessary power connection without having to \"stretch\" the CPU power connector from the power supply.", "title": "StarTech.com 8-Inch ATX12V 4-Pin P4 CPU Power Extension Cable (ATXP4EXT)", "price": 3.33, "imUrl": "http://ecx.images-amazon.com/images/I/41vQB9dQotL._SY300_.jpg", "brand": "StarTech", "related": {"also_bought": ["B000FL60AI", "B000M802RG", "B00552PMWE", "B0036ORCHG", "B004ZMYBAE", "B005KQ68BE", "B0002GRTZQ", "B000BX4J9O", "B002O21XHQ", "B0036ORCJY", "B000H9J3ZC", "B0007RXDDM", "B0027AGK3M", "B00066IO2O", "B002G1YNR2", "B00BR6XJRW", "B00009YFTI", "B000FAKUE6", "B002DY7M1G", "B0026ZPFCK", "B004RI5EHA", "B0058DN7B8", "B009VCAJ7W", "B002N2EHVQ", "B00EAXISZW", "B001PI9AAC", "B0064LWISQ", "B0002GRUV4", "B0088PUEPK", "B0098FSJ92", "B0012SM2SC", "B000OGX5AM", "B002G1YNQS", "B0045DUX5A", "B002BFNZAO", "B004E5OR74", "B00JEJZ1N4", "B0033Z2BAQ", "B009JXKQ9O", "B00DYQSZ68", "B00J8E92R6", "B002YIG9AQ", "B003L18WTQ", "B003AI272I", "B00I6DLK3O", "B00E3W15P0", "B004MU8VCS", "B007BPOC7O", "B0095VPBM2", "B003ZDNXZI", "B002OFP6QW", "B00957SY6G", "B00B46XJ4S", "B0057Q4AGW", "B00E20SSZ8", "B00126U0VA", "B000067SCY", "B00I6BJATW", "B00008VFAU", "B00G57BN1M", "B000O8I474", "B004YDVE1S", "B005TWE6B8", "B00ID0V88C", "B0086OGN9E", "B00A1ZTZOG", "B005VRGGGO", "B001O4EPHA", "B00BQY36DC", "B00H09BOXQ", "B00CPLGGWS", "B005W0UVCU", "B007S3T4O0", "B00B46XKKQ", "B005T3GRNW", "B0046U6DWO", "B00CB2MT1S", "B005C31GIA", "B009GULFJ0", "B00C7BJTU2", "B0092ML0OC", "B002L16OMO", "B009O7YORK", "B00H33SDR4", "B00598DMOO", "B00213KDQK", "B0046U6DTC", "B00HZ0M9F2", "B002TW03X6", "B005DD28XG", "B005CTCD6S", "B00EUAFAF6", "B006DKER46", "B00CO8T9VM", "B000NBKLOQ", "B002LBROAA", "B002Q2M8KK", "B006P61KH0", "B0032UUGF4"], "bought_together": ["B000FL60AI", "B000M802RG"], "buy_after_viewing": ["B00066IO2O", "B00BR6XJRW", "B002O21XHQ", "B000BX4J9O"]}}