{"asin": "B00BTISDW4", "related": {"also_viewed": ["B00JXM0CAE", "B00HVG5ZZ6", "B003ES7GRA", "B00I3V8ZG4", "B003FTSB6S", "B008F5FBY2", "B0051A5PCC", "B004I27M4S", "B005IVKCNQ", "B000RZQGS8", "B002MQ462I", "B00ETK9X1O", "B00JOSEHTO", "B0051A0E6Y", "B00J8OTIHU", "B005FPDCOG", "B004I26GJA", "B00FPU1V7G", "B000CSLJDW", "B004E8SLX2", "B003YC6J0G", "B003AJJTXM", "B0027A8L6Q", "B00GVDUS0W", "B002PI3WPA", "B00EY0O31E", "B00KJUNL34", "B00BWO5IO6", "B00F060OB4", "B007ZXR4I6", "B00CYDSAO4", "B003ZZBINA", "B00L3IWTMU", "B000KTXASA", "B00I3LCU3I", "B00H1NWX8Q", "B00CK6ZWUA", "B00GZW35U4", "B00H4B37IA", "B00F9YDA2W", "B00AZTEX04", "B0088QX50U", "B003ZX0QD0", "B00GR4SSPW", "B004HGOF4K", "B005NLOLLU", "B001DXH5NS", "B00B76ALVO", "B00BLIMB2U", "B00CFRBIC0", "B00CFS8ROG", "B003P69QIS", "B00A6M17XQ", "B004I29MWS", "B0041TGNCU", "B00JSORS40", "B002N0U37A", "B00B2WYA2Y"]}, "title": "GHD Candy Collection Professional Styler, Classic Lemon, Yellow, 1 Inch", "price": 199.0, "salesRank": {"Beauty": 232850}, "imUrl": "http://ecx.images-amazon.com/images/I/41%2BgB8pZHjL._SX300_.jpg", "brand": "ghd PROFESSIONAL", "categories": [["Beauty", "Hair Care", "Styling Tools", "Irons", "Flattening Irons"]], "description": "Limited edition candy collection 1\" professional styler. Classic lemon. Original ceramic heat technology, can use as a styler for great curls or a perfect glossy straight finish! Sleep mode switches the tool off after it hasn't been used for 30mins."}